LICENSE
LICENSE.txt
README.md
setup.cfg
setup.py
citipy/__init__.py
citipy/citipy.py
citipy/worldcities.csv
citipy.egg-info/PKG-INFO
citipy.egg-info/SOURCES.txt
citipy.egg-info/dependency_links.txt
citipy.egg-info/requires.txt
citipy.egg-info/top_level.txt